canarytrap/__init__.py
canarytrap/text.py
tests/__init__.py
tests/test_text.py
canarytrap-1.0.2.dist-info/LICENSE
canarytrap-1.0.2.dist-info/METADATA
canarytrap-1.0.2.dist-info/WHEEL
canarytrap-1.0.2.dist-info/top_level.txt
canarytrap-1.0.2.dist-info/RECORD
