Metadata-Version: 2.1
Name: canarytrap
Version: 1.0.2
Summary: A Python package to watermark text.
Home-page: https://github.com/MatthewLeeCode/CanaryTrap
Author: Matthew Lee
Author-email: matthewleemattner@gmail.com
Requires-Python: >=3.9
License-File: LICENSE
